AccessControl/AuthEncoding.py
AccessControl/ImplC.py
AccessControl/ImplPython.py
AccessControl/Implementation.py
AccessControl/Owned.py
AccessControl/Permission.py
AccessControl/PermissionMapping.py
AccessControl/PermissionRole.py
AccessControl/Permissions.py
AccessControl/Role.py
AccessControl/SecurityInfo.py
AccessControl/SecurityManagement.py
AccessControl/SecurityManager.py
AccessControl/SimpleObjectPolicies.py
AccessControl/SpecialUsers.py
AccessControl/User.py
AccessControl/ZopeGuards.py
AccessControl/ZopeSecurityPolicy.py
AccessControl/__init__.py
AccessControl/_compat.h
AccessControl/cAccessControl.c
AccessControl/cAccessControl.cpython-314-darwin.so
AccessControl/class_init.py
AccessControl/configure.zcml
AccessControl/interfaces.py
AccessControl/logger_wrapper.py
AccessControl/meta.zcml
AccessControl/metaconfigure.py
AccessControl/owner.py
AccessControl/permissions.zcml
AccessControl/requestmethod.py
AccessControl/rolemanager.py
AccessControl/safe_formatter.py
AccessControl/security.py
AccessControl/tainted.py
AccessControl/unauthorized.py
AccessControl/userfolder.py
AccessControl/users.py
AccessControl/tests/__init__.py
AccessControl/tests/actual_python.py
AccessControl/tests/testClassSecurityInfo.py
AccessControl/tests/testImplementation.py
AccessControl/tests/testModuleSecurity.py
AccessControl/tests/testPermissionMapping.py
AccessControl/tests/testPermissionRole.py
AccessControl/tests/testSecurityManager.py
AccessControl/tests/testZCML.py
AccessControl/tests/testZopeGuards.py
AccessControl/tests/testZopeSecurityPolicy.py
AccessControl/tests/test_owner.py
AccessControl/tests/test_requestmethod.py
AccessControl/tests/test_rolemanager.py
AccessControl/tests/test_safe_formatter.py
AccessControl/tests/test_safeiter.py
AccessControl/tests/test_tainted.py
AccessControl/tests/test_userfolder.py
AccessControl/tests/test_users.py
AccessControl/tests/mixed_module/__init__.py
AccessControl/tests/mixed_module/submodule/__init__.py
accesscontrol-7.3.dist-info/licenses/LICENSE.txt
accesscontrol-7.3.dist-info/METADATA
accesscontrol-7.3.dist-info/WHEEL
accesscontrol-7.3.dist-info/entry_points.txt
accesscontrol-7.3.dist-info/top_level.txt
accesscontrol-7.3.dist-info/RECORD
